yolomosaic/__init__.py
yolomosaic/cli.py
yolomosaic/ymosaic.py
yolomosaic/computer_vision/__init__.py
yolomosaic/computer_vision/model_inference.py
yolomosaic/geo_processing/__init__.py
yolomosaic/geo_processing/geo.py
yolomosaic/orthomosaic/__init__.py
yolomosaic/orthomosaic/orthomosaic_preprocessing.py
yolomosaic/utils/__init__.py
yolomosaic/utils/general.py
yolomosaic-0.1.2.3.dist-info/LICENSE
yolomosaic-0.1.2.3.dist-info/METADATA
yolomosaic-0.1.2.3.dist-info/WHEEL
yolomosaic-0.1.2.3.dist-info/entry_points.txt
yolomosaic-0.1.2.3.dist-info/top_level.txt
yolomosaic-0.1.2.3.dist-info/RECORD
