Metadata-Version: 2.1
Name: yolomosaic
Version: 0.1.2.3
Summary: A Python library for visualizing YOLO detections and segmented instances on large orthomosaic images, with the ability to generate shapefiles for GIS integration
Home-page: https://github.com/jithin8mathew/YOLOmosaic
Author: Jithin Mathew
License: MIT
Classifier: Programming Language :: Python :: 3
Classifier: Programming Language :: Python :: 3.7
Classifier: License :: OSI Approved :: MIT License
Classifier: Operating System :: OS Independent
Requires-Python: >=3.6
License-File: LICENSE
Requires-Dist: sahi (==0.11.20)
Requires-Dist: geopandas (==1.0.1)
Requires-Dist: ultralytics (==8.3.27)
Requires-Dist: ultralytics-thop (==2.0.13)
Requires-Dist: torch (==2.5.0)
Requires-Dist: torchaudio (>=2.5.0)
Requires-Dist: torchvision
Requires-Dist: pandas (==2.2.3)
Requires-Dist: numpy (==1.26.0)
Requires-Dist: rasterio
Requires-Dist: shapely
